internalreferences.py
pandoc_internal_references-0.5.dist-info/WHEEL
pandoc_internal_references-0.5.dist-info/top_level.txt
pandoc_internal_references-0.5.dist-info/entry_points.txt
pandoc_internal_references-0.5.dist-info/metadata.json
pandoc_internal_references-0.5.dist-info/RECORD
pandoc_internal_references-0.5.dist-info/DESCRIPTION.rst
pandoc_internal_references-0.5.dist-info/METADATA
