Metadata-Version: 2.0
Name: pandoc-internal-references
Version: 0.5
Summary: Image attributes and internal referencing in markdown
Home-page: https://github.com/aaren/pandoc-reference-filter
Author: Aaron O'Leary
Author-email: dev@aaren.me
License: BSD 2-Clause
Platform: UNKNOWN
Requires-Dist: pandocfilters
Requires-Dist: pandoc-attributes
